{"version": "4.5.7", "flags": {}, "shapes": [{"label": "null", "points": [[350.0, 661.0], [573.0, 660.0], [574.0, 688.0], [349.0, 691.0]], "group_id": 0, "shape_type": "polygon", "flags": {}}, {"label": "null", "points": [[665.0, 660.0], [905.0, 667.0], [906.0, 696.0], [666.0, 693.0]], "group_id": 0, "shape_type": "polygon", "flags": {}}, {"label": "null", "points": [[277.0, 705.3816793893129], [719.4656488549618, 701.9083969465648], [721.7557251908397, 733.9694656488549], [276.0, 737.3816793893129]], "group_id": 3, "shape_type": "polygon", "flags": {}}, {"label": "null", "points": [[53.0, 684.0], [113.0, 683.0], [107.0, 718.0], [56.0, 720.0]], "group_id": 0, "shape_type": "polygon", "flags": {}}, {"label": "null", "points": [[904.0, 710.0], [1000.0, 714.0], [1001.0, 745.0], [902.0, 742.0]], "group_id": 0, "shape_type": "polygon", "flags": {}}, {"label": "null", "points": [[283.22981366459624, 514.2857142857142], [1008.695652173913, 522.360248447205], [1008.695652173913, 654.0372670807453], [268.0, 652.0]], "group_id": 0, "shape_type": "polygon", "flags": {}}], "imagePath": "img_3116.jpg", "imageData": "null", "imageHeight": 1024, "imageWidth": 1136}