{"version": "4.5.6", "flags": {}, "shapes": [{"label": "null", "points": [[485, 468], [512, 462], [509, 651], [483, 657]], "group_id": 0, "shape_type": "polygon", "flags": {}}, {"label": "null", "points": [[537, 793], [630, 820], [630, 844], [535, 817]], "group_id": 2, "shape_type": "polygon", "flags": {}}, {"label": "null", "points": [[541, 211], [627, 251], [638, 506], [538, 472]], "group_id": 0, "shape_type": "polygon", "flags": {}}, {"label": "null", "points": [[96, 1012], [131, 1004], [139, 1024], [96, 1024]], "group_id": 255, "shape_type": "polygon", "flags": {}}, {"label": "null", "points": [[567, 496], [617, 509], [611, 800], [561, 786]], "group_id": 0, "shape_type": "polygon", "flags": {}}, {"label": "null", "points": [[474, 776], [515, 768], [515, 777], [474, 783]], "group_id": 5, "shape_type": "polygon", "flags": {}}, {"label": "null", "points": [[476, 762], [514, 756], [514, 769], [476, 776]], "group_id": 2, "shape_type": "polygon", "flags": {}}, {"label": "null", "points": [[476, 750], [514, 744], [514, 755], [476, 761]], "group_id": 5, "shape_type": "polygon", "flags": {}}, {"label": "null", "points": [[476, 734], [510, 728], [510, 743], [476, 749]], "group_id": 5, "shape_type": "polygon", "flags": {}}, {"label": "null", "points": [[510, 729], [515, 727], [515, 743], [510, 744]], "group_id": 5, "shape_type": "polygon", "flags": {}}], "imagePath": "img_3577.jpg", "imageData": "null", "imageWidth": 1024, "imageHeight": 1024}