{"version": "4.5.6", "flags": {}, "shapes": [{"label": "null", "points": [[95, 639], [230, 700], [226, 1061], [75, 1014]], "group_id": 0, "shape_type": "polygon", "flags": {}}, {"label": "null", "points": [[78, 1022], [132, 1037], [125, 1250], [71, 1239]], "group_id": 0, "shape_type": "polygon", "flags": {}}, {"label": "null", "points": [[133, 1032], [181, 1050], [177, 1263], [130, 1252]], "group_id": 0, "shape_type": "polygon", "flags": {}}, {"label": "null", "points": [[182, 1050], [228, 1062], [226, 1276], [177, 1264]], "group_id": 0, "shape_type": "polygon", "flags": {}}, {"label": "null", "points": [[802, 1195], [843, 1182], [843, 1206], [805, 1217]], "group_id": 5, "shape_type": "polygon", "flags": {}}], "imagePath": "img_1868.jpg", "imageData": "null", "imageWidth": 1024, "imageHeight": 1365}