{"version": "4.5.6", "flags": {}, "shapes": [{"label": "null", "points": [[313.0, 476.0], [368.0, 473.0], [372.0, 786.0], [317.0, 784.0]], "group_id": 0, "shape_type": "polygon", "flags": {}}, {"label": "null", "points": [[210.0, 469.0], [265.0, 472.0], [270.0, 792.0], [207.0, 791.0]], "group_id": 0, "shape_type": "polygon", "flags": {}}, {"label": "null", "points": [[0.0, 824.0], [25.0, 825.0], [25.0, 845.0], [0.0, 842.0]], "group_id": 255, "shape_type": "polygon", "flags": {}}], "imagePath": "img_3159.jpg", "imageData": "null", "imageHeight": 1365, "imageWidth": 1024}