{"version": "4.5.7", "flags": {}, "shapes": [{"label": "null", "points": [[382.0, 165.0], [472.0, 137.0], [439.7391304347825, 1206.246376811594], [354.231884057971, 1227.9855072463768]], "group_id": 3, "shape_type": "polygon", "flags": {}}, {"label": "null", "points": [[347.0, 1234.0], [445.0, 1217.0], [443.0, 1264.0], [345.0, 1276.0]], "group_id": 2, "shape_type": "polygon", "flags": {}}, {"label": "null", "points": [[1012.0, 1040.0], [1023.0, 1039.0], [1024.0, 1317.0], [1009.0, 1318.0]], "group_id": 255, "shape_type": "polygon", "flags": {}}, {"label": "null", "points": [[989.0, 1115.0], [1007.0, 1112.0], [1004.0, 1327.0], [988.0, 1329.0]], "group_id": 2, "shape_type": "polygon", "flags": {}}, {"label": "null", "points": [[998.0, 958.0], [1023.0, 952.0], [1023.0, 995.0], [997.0, 999.0]], "group_id": 2, "shape_type": "polygon", "flags": {}}], "imagePath": "img_732.jpg", "imageData": "null", "imageHeight": 1365, "imageWidth": 1024}