{"version": "4.5.6", "flags": {}, "shapes": [{"label": "null", "points": [[350.0, 876.0], [446.0, 886.0], [445.0, 906.0], [350.0, 898.0]], "group_id": 2, "shape_type": "polygon", "flags": {}}, {"label": "null", "points": [[407.0, 409.0], [441.0, 425.0], [474.0, 536.0], [356.0, 508.0]], "group_id": 4, "shape_type": "polygon", "flags": {}}, {"label": "null", "points": [[597.0, 335.0], [628.0, 343.0], [662.0, 453.0], [560.0, 432.0]], "group_id": 4, "shape_type": "polygon", "flags": {}}, {"label": "null", "points": [[821.0, 484.0], [840.0, 480.0], [844.0, 509.0], [823.0, 514.0]], "group_id": 4, "shape_type": "polygon", "flags": {}}, {"label": "null", "points": [[822.0, 780.0], [841.0, 780.0], [848.0, 810.0], [823.0, 814.0]], "group_id": 4, "shape_type": "polygon", "flags": {}}, {"label": "null", "points": [[44.0, 694.0], [135.0, 703.0], [132.0, 729.0], [41.0, 718.0]], "group_id": 2, "shape_type": "polygon", "flags": {}}, {"label": "null", "points": [[423.4177215189873, 719.620253164557], [436.70886075949363, 720.5696202531645], [435.0, 832.0], [420.0, 832.0]], "group_id": 5, "shape_type": "polygon", "flags": {}}, {"label": "null", "points": [[427.53164556962025, 575.9493670886076], [441.4556962025316, 579.1139240506329], [439.0, 690.0], [423.0, 687.0]], "group_id": 5, "shape_type": "polygon", "flags": {}}, {"label": "null", "points": [[166.0, 809.0], [173.0, 805.0], [172.0, 826.0], [165.0, 826.0]], "group_id": 255, "shape_type": "polygon", "flags": {}}, {"label": "null", "points": [[67.0, 813.0], [74.0, 811.0], [70.0, 851.0], [64.0, 851.0]], "group_id": 255, "shape_type": "polygon", "flags": {}}, {"label": "null", "points": [[45.0, 959.0], [50.0, 958.0], [51.0, 971.0], [44.0, 971.0]], "group_id": 5, "shape_type": "polygon", "flags": {}}, {"label": "null", "points": [[51.0, 879.0], [57.0, 879.0], [57.0, 892.0], [50.0, 893.0]], "group_id": 5, "shape_type": "polygon", "flags": {}}, {"label": "null", "points": [[367.0, 557.0], [412.0, 562.0], [408.0, 842.0], [361.0, 837.0]], "group_id": 0, "shape_type": "polygon", "flags": {}}, {"label": "null", "points": [[392.0, 857.0], [439.0, 860.0], [439.0, 881.0], [392.0, 878.0]], "group_id": 2, "shape_type": "polygon", "flags": {}}, {"label": "null", "points": [[107.0, 764.0], [146.0, 775.0], [137.0, 947.0], [95.0, 943.0]], "group_id": 0, "shape_type": "polygon", "flags": {}}, {"label": "null", "points": [[81.0, 948.0], [149.0, 954.0], [147.0, 975.0], [82.0, 968.0]], "group_id": 2, "shape_type": "polygon", "flags": {}}, {"label": "null", "points": [[67.0, 360.0], [149.0, 388.0], [136.0, 642.0], [56.0, 641.0]], "group_id": 0, "shape_type": "polygon", "flags": {}}, {"label": "null", "points": [[46.0, 669.0], [107.0, 677.0], [108.0, 701.0], [42.0, 694.0]], "group_id": 0, "shape_type": "polygon", "flags": {}}], "imagePath": "img_3462.jpg", "imageData": "null", "imageHeight": 1024, "imageWidth": 1024}