{"version": "4.5.7", "flags": {}, "shapes": [{"label": "null", "points": [[504.0, 970.0], [714.1935483870967, 950.0], [712.5806451612902, 979.6774193548387], [504.0, 1008.0]], "group_id": 3, "shape_type": "polygon", "flags": {}}, {"label": "null", "points": [[533.0357142857142, 892.4107142857142], [715.1785714285713, 853.1249999999999], [710.7678571428572, 918.4464285714286], [526.7678571428572, 942.4464285714286]], "group_id": 0, "shape_type": "polygon", "flags": {}}, {"label": "null", "points": [[526.0, 942.0], [715.0, 918.0], [711.0, 937.0], [527.0, 954.0]], "group_id": 2, "shape_type": "polygon", "flags": {}}, {"label": "null", "points": [[380.0, 956.0], [510.71428571428567, 939.7321428571428], [510.71428571428567, 954.017857142857], [379.0, 971.0]], "group_id": 5, "shape_type": "polygon", "flags": {}}, {"label": "null", "points": [[508.0, 894.0], [528.0, 891.0], [528.0, 905.0], [508.0, 907.0]], "group_id": 2, "shape_type": "polygon", "flags": {}}, {"label": "null", "points": [[379.9107142857143, 910.2678571428571], [493.3035714285714, 895.5357142857142], [509.0, 938.0], [383.0, 954.0]], "group_id": 2, "shape_type": "polygon", "flags": {}}, {"label": "null", "points": [[314.0, 993.0], [497.0, 970.0], [495.0, 1009.0], [312.258064516129, 1030.0]], "group_id": 0, "shape_type": "polygon", "flags": {}}], "imagePath": "img_2603.jpg", "imageData": "null", "imageHeight": 1365, "imageWidth": 1024}