{"version": "4.5.6", "flags": {}, "shapes": [{"label": "null", "points": [[571, 1055], [580, 1058], [567, 1127], [558, 1117]], "group_id": 2, "shape_type": "polygon", "flags": {}}, {"label": "null", "points": [[563, 1063], [570, 1063], [562, 1110], [555, 1106]], "group_id": 5, "shape_type": "polygon", "flags": {}}, {"label": "null", "points": [[160, 88], [312, 134], [351, 1334], [112, 1313]], "group_id": 0, "shape_type": "polygon", "flags": {}}], "imagePath": "img_1626.jpg", "imageData": "null", "imageWidth": 1024, "imageHeight": 1365}