{"version": "4.5.7", "flags": {}, "shapes": [{"label": "null", "points": [[415.0, 924.0], [497.0, 917.0], [476.0, 1313.0], [388.0, 1314.0]], "group_id": 0, "shape_type": "polygon", "flags": {}}, {"label": "null", "points": [[420.0, 820.7821350762528], [501.0, 820.7821350762528], [501.0, 855.7821350762528], [420.0, 855.7821350762528]], "group_id": 5, "shape_type": "polygon", "flags": {}}, {"label": "null", "points": [[415.0, 867.0], [502.0, 855.0], [499.0, 907.0], [414.0, 911.0]], "group_id": 5, "shape_type": "polygon", "flags": {}}], "imagePath": "img_2113.jpg", "imageData": "null", "imageHeight": 1365, "imageWidth": 1024}