{"version": "4.5.6", "flags": {}, "shapes": [{"label": "null", "points": [[208.0, 1042.0], [246.0, 1034.0], [247.0, 1097.0], [206.0, 1098.0]], "group_id": 0, "shape_type": "polygon", "flags": {}}, {"label": "null", "points": [[151.0, 1024.0], [200.0, 1000.0], [208.0, 1125.0], [154.0, 1122.0]], "group_id": 0, "shape_type": "polygon", "flags": {}}, {"label": "null", "points": [[272.0, 1069.0], [294.0, 1065.0], [295.0, 1080.0], [272.0, 1084.0]], "group_id": 5, "shape_type": "polygon", "flags": {}}, {"label": "null", "points": [[505.0, 957.0], [708.0, 967.0], [738.0, 1108.0], [513.0, 1090.0]], "group_id": 0, "shape_type": "polygon", "flags": {}}, {"label": "null", "points": [[565.0, 1136.0], [690.0, 1137.0], [718.0, 1258.0], [563.0, 1218.0]], "group_id": 0, "shape_type": "polygon", "flags": {}}, {"label": "null", "points": [[592.0, 1261.0], [661.0, 1262.0], [660.0, 1297.0], [590.0, 1296.0]], "group_id": 0, "shape_type": "polygon", "flags": {}}, {"label": "null", "points": [[757.0, 1006.0], [912.0, 1014.0], [908.0, 1096.0], [747.0, 1092.0]], "group_id": 0, "shape_type": "polygon", "flags": {}}, {"label": "null", "points": [[295.0, 1064.0], [332.0, 1057.0], [332.0, 1073.0], [296.0, 1080.0]], "group_id": 5, "shape_type": "polygon", "flags": {}}, {"label": "null", "points": [[592.0, 1229.0], [636.0, 1228.0], [637.0, 1249.0], [593.0, 1246.0]], "group_id": 5, "shape_type": "polygon", "flags": {}}, {"label": "null", "points": [[271.0, 1043.0], [300.0, 1036.0], [300.0, 1058.0], [271.0, 1063.0]], "group_id": 2, "shape_type": "polygon", "flags": {}}, {"label": "null", "points": [[302.0, 1036.0], [333.0, 1029.0], [332.0, 1050.0], [301.0, 1056.0]], "group_id": 2, "shape_type": "polygon", "flags": {}}, {"label": "null", "points": [[575.0, 1228.0], [590.0, 1230.0], [590.0, 1245.0], [572.0, 1244.0]], "group_id": 4, "shape_type": "polygon", "flags": {}}, {"label": "null", "points": [[565.0, 1291.0], [580.0, 1291.0], [579.0, 1314.0], [561.0, 1312.0]], "group_id": 4, "shape_type": "polygon", "flags": {}}, {"label": "null", "points": [[592.0, 1302.0], [644.0, 1302.0], [644.0, 1317.0], [591.0, 1315.0]], "group_id": 2, "shape_type": "polygon", "flags": {}}, {"label": "null", "points": [[649.0, 1303.0], [700.0, 1304.0], [700.0, 1317.0], [648.0, 1317.0]], "group_id": 2, "shape_type": "polygon", "flags": {}}, {"label": "null", "points": [[204.0, 1021.0], [227.0, 1013.0], [228.0, 1033.0], [203.0, 1037.0]], "group_id": 5, "shape_type": "polygon", "flags": {}}], "imagePath": "img_3639.jpg", "imageData": "null", "imageHeight": 1365, "imageWidth": 1024}