{"version": "4.5.7", "flags": {}, "shapes": [{"label": "null", "points": [[846.0, 230.0], [1222.0, 221.0], [1223.0, 281.0], [844.0, 297.0]], "group_id": 0, "shape_type": "polygon", "flags": {}}, {"label": "null", "points": [[659.5890410958905, 869.1780821917808], [1023.0, 863.0], [1027.0, 929.0], [652.0, 936.0]], "group_id": 0, "shape_type": "polygon", "flags": {}}, {"label": "null", "points": [[957.0, 311.0], [1222.0, 310.0], [1224.0, 328.0], [960.0, 334.0]], "group_id": 5, "shape_type": "polygon", "flags": {}}, {"label": "null", "points": [[759.0, 311.561797752809], [921.0, 311.561797752809], [923.0, 336.561797752809], [759.0, 341.561797752809]], "group_id": 2, "shape_type": "polygon", "flags": {}}, {"label": "null", "points": [[614.0, 317.0], [725.0, 314.0], [727.0, 340.0], [614.0, 343.0]], "group_id": 2, "shape_type": "polygon", "flags": {}}, {"label": "null", "points": [[322.3150684931507, 839.6301369863014], [581.3150684931506, 836.6301369863014], [589.3150684931506, 939.6301369863014], [321.3150684931507, 947.6301369863014]], "group_id": 0, "shape_type": "polygon", "flags": {}}, {"label": "null", "points": [[1166.0, 438.0], [1205.0, 441.0], [1188.0, 695.0], [1155.0, 691.0]], "group_id": 5, "shape_type": "polygon", "flags": {}}, {"label": "null", "points": [[1218.0, 417.0], [1305.0, 413.0], [1293.0, 704.0], [1197.0, 707.0]], "group_id": 5, "shape_type": "polygon", "flags": {}}, {"label": "null", "points": [[765.0, 951.0], [1021.0, 944.0], [1023.0, 971.0], [766.0, 976.0]], "group_id": 2, "shape_type": "polygon", "flags": {}}, {"label": "null", "points": [[575.0, 954.0], [733.0, 952.0], [737.0, 978.0], [574.0, 982.0]], "group_id": 2, "shape_type": "polygon", "flags": {}}, {"label": "null", "points": [[325.0, 955.0], [545.0, 954.0], [548.0, 983.0], [332.0, 983.0]], "group_id": 2, "shape_type": "polygon", "flags": {}}, {"label": "null", "points": [[505.0, 213.0], [761.0, 201.0], [770.0, 300.0], [502.0, 301.0]], "group_id": 0, "shape_type": "polygon", "flags": {}}, {"label": "null", "points": [[503.0, 318.0], [577.0, 322.0], [579.0, 343.0], [503.0, 344.0]], "group_id": 2, "shape_type": "polygon", "flags": {}}], "imagePath": "img_2950.jpg", "imageData": "null", "imageHeight": 1024, "imageWidth": 1460}