{"version": "4.5.6", "flags": {}, "shapes": [{"label": "null", "points": [[484, 462], [568, 446], [564, 476], [478, 499]], "group_id": 2, "shape_type": "polygon", "flags": {}}, {"label": "null", "points": [[119, 830], [138, 830], [127, 866], [106, 866]], "group_id": 2, "shape_type": "polygon", "flags": {}}, {"label": "null", "points": [[149, 799], [212, 790], [205, 820], [140, 826]], "group_id": 5, "shape_type": "polygon", "flags": {}}, {"label": "null", "points": [[154, 825], [197, 822], [191, 840], [148, 842]], "group_id": 5, "shape_type": "polygon", "flags": {}}, {"label": "null", "points": [[705, 340], [1127, 233], [1153, 357], [703, 453]], "group_id": 0, "shape_type": "polygon", "flags": {}}, {"label": "null", "points": [[287, 451], [471, 401], [455, 507], [251, 552]], "group_id": 0, "shape_type": "polygon", "flags": {}}, {"label": "null", "points": [[130, 852], [141, 851], [137, 867], [127, 865]], "group_id": 5, "shape_type": "polygon", "flags": {}}, {"label": "null", "points": [[132, 800], [146, 800], [139, 828], [122, 828]], "group_id": 4, "shape_type": "polygon", "flags": {}}, {"label": "null", "points": [[266, 2], [293, 0], [383, 102], [374, 131]], "group_id": 0, "shape_type": "polygon", "flags": {}}, {"label": "null", "points": [[258, 0], [384, 145], [374, 175], [240, 24]], "group_id": 2, "shape_type": "polygon", "flags": {}}, {"label": "null", "points": [[579, 442], [667, 423], [664, 456], [573, 475]], "group_id": 2, "shape_type": "polygon", "flags": {}}, {"label": "null", "points": [[499, 396], [677, 354], [671, 415], [490, 454]], "group_id": 0, "shape_type": "polygon", "flags": {}}, {"label": "null", "points": [[142, 842], [197, 838], [190, 856], [138, 860]], "group_id": 5, "shape_type": "polygon", "flags": {}}], "imagePath": "img_3729.jpg", "imageData": "null", "imageWidth": 1257, "imageHeight": 1024}