{"version": "4.5.7", "flags": {}, "shapes": [{"label": "null", "points": [[50.0, 953.0], [378.0, 938.0], [376.0, 1024.0], [38.0, 1024.0]], "group_id": 0, "shape_type": "polygon", "flags": {}}, {"label": "null", "points": [[990.0, 912.0], [1098.0, 911.0], [1103.0, 930.0], [995.0, 936.0]], "group_id": 0, "shape_type": "polygon", "flags": {}}, {"label": "null", "points": [[999.0, 947.0], [1107.0, 940.0], [1115.0, 964.0], [1004.0, 971.0]], "group_id": 2, "shape_type": "polygon", "flags": {}}, {"label": "null", "points": [[1009.0, 993.0], [1122.0, 986.0], [1125.0, 1001.0], [1014.0, 1010.0]], "group_id": 5, "shape_type": "polygon", "flags": {}}], "imagePath": "img_1818.jpg", "imageData": "null", "imageHeight": 1024, "imageWidth": 1391}