{"version": "4.5.7", "flags": {}, "shapes": [{"label": "null", "points": [[493.0, 848.0], [709.8039215686274, 849.6732026143791], [707.843137254902, 863.3986928104575], [490.0, 868.0]], "group_id": 3, "shape_type": "polygon", "flags": {}}, {"label": "null", "points": [[1241.0, 1000.0], [1272.0, 1000.0], [1272.0, 1024.0], [1241.0, 1024.0]], "group_id": 255, "shape_type": "polygon", "flags": {}}, {"label": "null", "points": [[83.0, 976.0], [108.0, 977.0], [104.0, 999.0], [80.0, 996.0]], "group_id": 255, "shape_type": "polygon", "flags": {}}, {"label": "null", "points": [[211.0, 717.0], [1131.5217391304348, 696.7391304347826], [1136.9565217391305, 761.9565217391304], [203.0, 782.0]], "group_id": 3, "shape_type": "polygon", "flags": {}}, {"label": "null", "points": [[186.0, 544.0], [1203.0, 481.0], [1219.0, 681.0], [153.0, 712.0]], "group_id": 0, "shape_type": "polygon", "flags": {}}, {"label": "null", "points": [[712.5, 852.0270270270271], [744.5945945945946, 849.3243243243244], [743.581081081081, 865.2027027027027], [711.4864864864865, 864.8648648648649]], "group_id": 255, "shape_type": "polygon", "flags": {}}], "imagePath": "img_1060.jpg", "imageData": "null", "imageHeight": 1024, "imageWidth": 1365}