{"version": "4.5.6", "flags": {}, "shapes": [{"label": "null", "points": [[241, 362], [530, 365], [529, 424], [242, 422]], "group_id": 0, "shape_type": "polygon", "flags": {}}, {"label": "null", "points": [[239, 627], [526, 627], [526, 689], [239, 689]], "group_id": 0, "shape_type": "polygon", "flags": {}}, {"label": "null", "points": [[238, 690], [525, 691], [524, 748], [240, 748]], "group_id": 0, "shape_type": "polygon", "flags": {}}, {"label": "null", "points": [[241, 493], [529, 495], [529, 555], [241, 555]], "group_id": 0, "shape_type": "polygon", "flags": {}}, {"label": "null", "points": [[241, 428], [529, 428], [529, 491], [242, 487]], "group_id": 0, "shape_type": "polygon", "flags": {}}, {"label": "null", "points": [[210, 557], [562, 557], [562, 611], [210, 611]], "group_id": 2, "shape_type": "polygon", "flags": {}}], "imagePath": "img_3179.jpg", "imageData": "null", "imageWidth": 1024, "imageHeight": 1365}