{"version": "4.5.7", "flags": {}, "shapes": [{"label": "null", "points": [[712.0, 602.0], [966.0, 602.0], [966.0, 659.0], [712.0, 659.0]], "group_id": 0, "shape_type": "polygon", "flags": {}}, {"label": "null", "points": [[57.0, 520.0], [698.4126984126984, 525.3968253968254], [696.031746031746, 585.7142857142857], [57.0, 586.0]], "group_id": 3, "shape_type": "polygon", "flags": {}}, {"label": "null", "points": [[196.0, 391.0], [843.0, 391.0], [843.0, 495.0], [196.0, 495.0]], "group_id": 0, "shape_type": "polygon", "flags": {}}, {"label": "null", "points": [[189.0, 283.0], [841.0, 283.0], [841.0, 391.0], [189.0, 391.0]], "group_id": 0, "shape_type": "polygon", "flags": {}}, {"label": "null", "points": [[62.0, 99.0], [947.0, 117.0], [958.0, 288.0], [79.0, 271.0]], "group_id": 0, "shape_type": "polygon", "flags": {}}, {"label": "null", "points": [[736.0, 659.0], [943.0, 659.0], [943.0, 715.0], [737.0, 715.0]], "group_id": 0, "shape_type": "polygon", "flags": {}}, {"label": "null", "points": [[315.07936507936506, 589.6825396825396], [699.2063492063492, 596.031746031746], [698.4126984126984, 651.5873015873016], [315.87301587301585, 654.7619047619047]], "group_id": 3, "shape_type": "polygon", "flags": {}}, {"label": "null", "points": [[318.25396825396825, 660.3174603174604], [695.2380952380952, 663.4920634920635], [692.063492063492, 719.047619047619], [319.8412698412698, 723.015873015873]], "group_id": 3, "shape_type": "polygon", "flags": {}}], "imagePath": "img_2239.jpg", "imageData": "null", "imageHeight": 1365, "imageWidth": 1024}