{"version": "4.5.6", "flags": {}, "shapes": [{"label": "null", "points": [[329, 1273], [543, 1273], [543, 1320], [329, 1320]], "group_id": 0, "shape_type": "polygon", "flags": {}}, {"label": "null", "points": [[606, 1233], [999, 1233], [999, 1326], [606, 1326]], "group_id": 0, "shape_type": "polygon", "flags": {}}, {"label": "null", "points": [[85, 1121], [601, 1121], [598, 1230], [85, 1232]], "group_id": 0, "shape_type": "polygon", "flags": {}}, {"label": "null", "points": [[90, 1269], [309, 1269], [310, 1320], [89, 1318]], "group_id": 0, "shape_type": "polygon", "flags": {}}], "imagePath": "img_2883.jpg", "imageData": "null", "imageWidth": 1024, "imageHeight": 1365}