{"version": "4.5.6", "flags": {}, "shapes": [{"label": "null", "points": [[381, 386], [759, 410], [767, 500], [387, 481]], "group_id": 2, "shape_type": "polygon", "flags": {}}, {"label": "null", "points": [[385, 491], [1225, 538], [1243, 598], [376, 550]], "group_id": 0, "shape_type": "polygon", "flags": {}}, {"label": "null", "points": [[825, 413], [1181, 433], [1214, 528], [830, 510]], "group_id": 2, "shape_type": "polygon", "flags": {}}], "imagePath": "img_971.jpg", "imageData": "null", "imageWidth": 1365, "imageHeight": 1024}