{"version": "4.5.6", "flags": {}, "shapes": [{"label": "null", "points": [[512, 943], [866, 954], [844, 1025], [483, 1016]], "group_id": 2, "shape_type": "polygon", "flags": {}}, {"label": "null", "points": [[849, 920], [886, 922], [878, 951], [846, 952]], "group_id": 2, "shape_type": "polygon", "flags": {}}, {"label": "null", "points": [[60, 741], [669, 751], [626, 867], [247, 1079]], "group_id": 0, "shape_type": "polygon", "flags": {}}, {"label": "null", "points": [[469, 874], [726, 877], [699, 950], [436, 944]], "group_id": 2, "shape_type": "polygon", "flags": {}}], "imagePath": "img_2474.jpg", "imageData": "null", "imageWidth": 1024, "imageHeight": 1365}